zpretty/__init__.py
zpretty/attributes.py
zpretty/cli.py
zpretty/elements.py
zpretty/prettifier.py
zpretty/text.py
zpretty/xml.py
zpretty/zcml.py
zpretty/tests/__init__.py
zpretty/tests/mock.py
zpretty/tests/test_attributes.py
zpretty/tests/test_cli.py
zpretty/tests/test_elements.py
zpretty/tests/test_functions.py
zpretty/tests/test_readme.py
zpretty/tests/test_xml.py
zpretty/tests/test_zcml.py
zpretty/tests/test_zpretty.py
zpretty/tests/broken/broken.xml
zpretty/tests/include-exclude/.venv/bar.html
zpretty/tests/include-exclude/.venv/bar.pt
zpretty/tests/include-exclude/.venv/bar.txt
zpretty/tests/include-exclude/.venv/bar.xml
zpretty/tests/include-exclude/.venv/bar.zcml
zpretty/tests/include-exclude/.venv/foo.html
zpretty/tests/include-exclude/.venv/foo.pt
zpretty/tests/include-exclude/.venv/foo.txt
zpretty/tests/include-exclude/.venv/foo.xml
zpretty/tests/include-exclude/.venv/foo.zcml
zpretty/tests/include-exclude/foo/bar/bar.html
zpretty/tests/include-exclude/foo/bar/bar.pt
zpretty/tests/include-exclude/foo/bar/bar.txt
zpretty/tests/include-exclude/foo/bar/bar.xml
zpretty/tests/include-exclude/foo/bar/bar.zcml
zpretty/tests/include-exclude/foo/bar/foo.html
zpretty/tests/include-exclude/foo/bar/foo.pt
zpretty/tests/include-exclude/foo/bar/foo.txt
zpretty/tests/include-exclude/foo/bar/foo.xml
zpretty/tests/include-exclude/foo/bar/foo.zcml
zpretty/tests/include-exclude/venv/bar.html
zpretty/tests/include-exclude/venv/bar.pt
zpretty/tests/include-exclude/venv/bar.txt
zpretty/tests/include-exclude/venv/bar.xml
zpretty/tests/include-exclude/venv/bar.zcml
zpretty/tests/include-exclude/venv/foo.html
zpretty/tests/include-exclude/venv/foo.pt
zpretty/tests/include-exclude/venv/foo.txt
zpretty/tests/include-exclude/venv/foo.xml
zpretty/tests/include-exclude/venv/foo.zcml
zpretty/tests/original/sample.txt
zpretty/tests/original/sample.zcml
zpretty/tests/original/sample_dtml.dtml
zpretty/tests/original/sample_html.html
zpretty/tests/original/sample_html4.html
zpretty-3.1.1.dist-info/licenses/LICENSE
zpretty-3.1.1.dist-info/METADATA
zpretty-3.1.1.dist-info/WHEEL
zpretty-3.1.1.dist-info/entry_points.txt
zpretty-3.1.1.dist-info/top_level.txt
zpretty-3.1.1.dist-info/RECORD
