Metadata-Version: 2.4
Name: zpretty
Version: 3.1.1
Summary: An opinionated HTML/XML soup formatter
Home-page: https://github.com/collective/zpretty
Author: Alessandro Pisa
Author-email: alessandro.pisa@gmail.com
License: BSD
Keywords: Formatter,HTML,Prettifier,Pretty print,TAL,XML,ZPT
Classifier: Development Status :: 5 - Production/Stable
Classifier: Environment :: Console
Classifier: Intended Audience :: Developers
Classifier: Programming Language :: Python
Classifier: Programming Language :: Python :: 3.7
Classifier: Programming Language :: Python :: 3.8
Classifier: Programming Language :: Python :: 3.9
Classifier: Programming Language :: Python :: 3.10
Classifier: Programming Language :: Python :: 3.11
Classifier: Programming Language :: Python :: 3.12
Classifier: Programming Language :: Python :: 3.13
Classifier: Programming Language :: Python :: 3 :: Only
Requires-Python: >=3.7
License-File: LICENSE
Requires-Dist: setuptools
Requires-Dist: beautifulsoup4
Requires-Dist: lxml
Provides-Extra: test
Requires-Dist: pre-commit; extra == "test"
Requires-Dist: pytest-cov; extra == "test"
Requires-Dist: pytest; extra == "test"
Provides-Extra: development
Requires-Dist: zest.releaser; extra == "development"
Requires-Dist: check-manifest; extra == "development"
Requires-Dist: pyroma; extra == "development"
Dynamic: author
Dynamic: author-email
Dynamic: classifier
Dynamic: description
Dynamic: description-content-type
Dynamic: home-page
Dynamic: keywords
Dynamic: license
Dynamic: license-file
Dynamic: provides-extra
Dynamic: requires-dist
Dynamic: requires-python
Dynamic: summary
